odoo/addons/stock_valuation_fifo_lot/README.rst
odoo/addons/stock_valuation_fifo_lot/__init__.py
odoo/addons/stock_valuation_fifo_lot/__manifest__.py
odoo/addons/stock_valuation_fifo_lot/i18n/stock_valuation_fifo_lot.pot
odoo/addons/stock_valuation_fifo_lot/models/__init__.py
odoo/addons/stock_valuation_fifo_lot/models/product.py
odoo/addons/stock_valuation_fifo_lot/models/stock_landed_cost.py
odoo/addons/stock_valuation_fifo_lot/models/stock_move.py
odoo/addons/stock_valuation_fifo_lot/models/stock_valuation_layer.py
odoo/addons/stock_valuation_fifo_lot/readme/CONTRIBUTORS.rst
odoo/addons/stock_valuation_fifo_lot/readme/DESCRIPTION.rst
odoo/addons/stock_valuation_fifo_lot/static/description/icon.png
odoo/addons/stock_valuation_fifo_lot/static/description/index.html
odoo/addons/stock_valuation_fifo_lot/views/stock_valuation_layer_views.xml
odoo_addon_stock_valuation_fifo_lot-15.0.1.0.0.5.dist-info/METADATA
odoo_addon_stock_valuation_fifo_lot-15.0.1.0.0.5.dist-info/WHEEL
odoo_addon_stock_valuation_fifo_lot-15.0.1.0.0.5.dist-info/top_level.txt
odoo_addon_stock_valuation_fifo_lot-15.0.1.0.0.5.dist-info/RECORD
